LICENSE
MANIFEST.in
README.md
setup.py
flask_appmanager/__init__.py
flask_appmanager.egg-info/PKG-INFO
flask_appmanager.egg-info/SOURCES.txt
flask_appmanager.egg-info/dependency_links.txt
flask_appmanager.egg-info/requires.txt
flask_appmanager.egg-info/top_level.txt