Metadata-Version: 2.1
Name: flask-appmanager
Version: 0.1.14
Summary: 一个Flask的后台插件
Home-page: https://gitee.com/toby_lai/flask_appmanager
Author: Lai_Pengtao
Author-email: toby_lai@126.com
License: MIT
Platform: UNKNOWN
Classifier: License :: OSI Approved :: MIT License
Classifier: Programming Language :: Python
Classifier: Programming Language :: Python :: 3
Classifier: Programming Language :: Python :: 3.6
Classifier: Programming Language :: Python :: Implementation :: CPython
Classifier: Programming Language :: Python :: Implementation :: PyPy
Requires-Python: >=3.6.0
